setup.py
simpletable.py
simpletable.egg-info/PKG-INFO
simpletable.egg-info/SOURCES.txt
simpletable.egg-info/dependency_links.txt
simpletable.egg-info/not-zip-safe
simpletable.egg-info/requires.txt
simpletable.egg-info/top_level.txt