Metadata-Version: 1.0
Name: simpletable
Version: 0.2.2
Summary: wrapper around pytables/hd5f to simplify using structured data
Home-page: http://bitbucket.org/brentp/biostuff/
Author: Brent Pedersen
Author-email: bpederse@gmail.com
License: BSD
Keywords: hdf5 pytables tables numpy
Platform: UNKNOWN
Classifier: Development Status :: 3 - Alpha
Classifier: Intended Audience :: Developers
Classifier: Intended Audience :: Science/Research
Classifier: License :: OSI Approved :: BSD License
Classifier: Operating System :: OS Independent
Classifier: Programming Language :: Python
Classifier: Topic :: Scientific/Engineering
Classifier: Topic :: Database
